augmented/__init__.py
augmented-2.4.1.dist-info/METADATA
augmented-2.4.1.dist-info/WHEEL
augmented-2.4.1.dist-info/top_level.txt
augmented-2.4.1.dist-info/RECORD
