Metadata-Version: 2.1
Name: augmented
Version: 2.4.1
Summary: Augmented reality in python made easy
Home-page: https://www.github.com/sarangt123/augmented
Author: Sarang T (github.com/sarangt123)
Author-email: sarang.thekkedathpr@gmail.com
License: BSD-3-Clause License
Keywords: Augmented reality
Platform: UNKNOWN
Classifier: Development Status :: 5 - Production/Stable
Classifier: Intended Audience :: Education
Classifier: Intended Audience :: Developers
Classifier: Operating System :: OS Independent
Classifier: License :: OSI Approved :: BSD License
Requires-Python: >=3.6
Requires-Dist: numpy (==1.19.5)
Requires-Dist: opencv-contrib-python (==4.5.3.56)
